taktkit/__init__.py
taktkit/static/taktkit/__pycache__/__init__.cpython-312.pyc
taktkit/static/taktkit/css/.gitkeep
taktkit/static/taktkit/css/taktkit.min.css
taktkit/static/taktkit/js/.gitkeep
taktkit/static/taktkit/js/taktkit.min.js
taktkit-0.1.0.dist-info/licenses/LICENSE
taktkit-0.1.0.dist-info/METADATA
taktkit-0.1.0.dist-info/WHEEL
taktkit-0.1.0.dist-info/top_level.txt
taktkit-0.1.0.dist-info/RECORD
